RepoGraph/RepoGraph.py
RepoGraph/__init__.py
RepoOutline/RepoOutline.py
RepoOutline/__init__.py
RepoOutline-0.1.0.dist-info/METADATA
RepoOutline-0.1.0.dist-info/WHEEL
RepoOutline-0.1.0.dist-info/entry_points.txt
RepoOutline-0.1.0.dist-info/top_level.txt
RepoOutline-0.1.0.dist-info/RECORD
