Metadata-Version: 2.1
Name: RepoOutline
Version: 0.1.0
Summary: A tool to generate a markdown representation of a repository structure.
Home-page: https://github.com/yourusername/repo-outline
Author: Tina Vue
Author-email: tina.vtt@gmail.com
License: UNKNOWN
Platform: UNKNOWN
Classifier: Programming Language :: Python :: 3
Classifier: License :: OSI Approved :: MIT License
Classifier: Operating System :: OS Independent
Requires-Python: >=3.6
